sample_sheet/__init__.py
sample_sheet/util.py
sample_sheet-0.8.0.data/scripts/sample-sheet
sample_sheet-0.8.0.dist-info/METADATA
sample_sheet-0.8.0.dist-info/RECORD
sample_sheet-0.8.0.dist-info/WHEEL
sample_sheet-0.8.0.dist-info/top_level.txt
sample_sheet-0.8.0.dist-info/zip-safe
