Metadata-Version: 2.1
Name: sample-sheet
Version: 0.8.0
Summary: An Illumina Sample Sheet parsing library
Home-page: https://github.com/clintval/sample-sheet
Author: clintval
Author-email: valentine.clint@gmail.com
License: MIT
Download-URL: https://github.com/sample-sheet/archive/v0.8.0.tar.gz
Project-URL: Documentation, https://sample-sheet.readthedocs.io
Project-URL: Issue-Tracker, https://github.com/clintval/sample-sheet/issues
Keywords: illumina samplesheet sample sheet parser bioinformatics
Platform: UNKNOWN
Classifier: Development Status :: 2 - Pre-Alpha
Classifier: Intended Audience :: Developers
Classifier: Intended Audience :: Science/Research
Classifier: License :: OSI Approved :: MIT License
Classifier: Topic :: Scientific/Engineering :: Bio-Informatics
Classifier: Programming Language :: Python :: 3.6
Classifier: Programming Language :: Python :: 3.7
Requires-Dist: click
Requires-Dist: smart-open (>=1.5.4)
Requires-Dist: tabulate
Requires-Dist: terminaltables
